parendumlib/__init__.py
parendumlib/exceptions.py
parendumlib/logger.py
parendumlib/mailer.py
parendumlib/responses.py
parendumlib/utils.py
parendumlib/database/__init__.py
parendumlib/database/mongodb.py
parendumlib/permissions/__init__.py
parendumlib/permissions/mongodb.py
ParendumLib-0.2.3.dist-info/METADATA
ParendumLib-0.2.3.dist-info/WHEEL
ParendumLib-0.2.3.dist-info/top_level.txt
ParendumLib-0.2.3.dist-info/RECORD
